[
    {
        "name": "ava",
        "posts": 
        [
            {
                "description": "hungry",
                "comments": [
                    {"name": "peanut", "comment": "cute"},
                    {"name": "tofu", "comment": "wna grab sum food?"},
                    {"name": "ava", "comment": "if you pay :3"},
                    {"name": "tofu", "comment": "nvm"}
                ]
            },
            {
                "description": "they made logs from fortnite a real thing",
                "comments": [
                    {"name": "miso", "comment": "thats crazy"},
                    {"name": "larson", "comment": "this is the stupidest thing i've ever read"},
                    {"name": "dexter", "comment": "cute"}
                ]
            }
        ]
    },
    {
        "name": "bao",
        "posts": 
        [
            {
                "description": "me and my best fren",
                "comments": [
                    {"name": "oreo", "comment": "i thought i was your best friend"},
                    {"name": "bao", "comment": "u were until u broke our litter box"},
                    {"name": "sesame", "comment": "L oreo"}
                ]
            }
        ]
    },
    {
        "name": "booboo",
        "posts": 
        [
            {
                "description": "ava told a funny joke",
                "comments": [
                    {"name": "shelby", "comment": "what was it"},
                    {"name": "ava", "comment": "inside joke you wouldn't get it"},
                    {"name": "shelby", "comment": "..."}
                ]
            },
            {
                "description": "me and my best friend!",
                "comments": [
                    {"name": "ava", "comment": "thats me!!"}
                ]
            }
        ]
    },
    {
        "name": "dexter",
        "posts": 
        [
            {
                "description": "i hate my roommate",
                "comments": [
                    {"name": "shelby", "comment": "why!!!"},
                    {"name": "dexter", "comment": "STOP EATING MY FOOD"},
                    {"name": "shelby", "comment": "u should've eaten faster then"}
                    
                ]
            }
        ]
    },
    {
        "name": "gomago",
        "posts": 
        [
            {
                "description": "hello!",
                "comments": [
                    {"name": "shelby", "comment": "Rest in peace <3"},
                    {"name": "dexter", "comment": "rip gomago"},
                    {"name": "sesame", "comment": "rest in peace, you will be missed"}
                ]
            }
        ]
    },
    {
        "name": "larson",
        "posts": 
        [
            {
                "description": ":3",
                "comments": [
                    {"name": "shelby", "comment": ":3"}
                ]
            }
        ]
    },
    {
        "name": "margot",
        "posts": 
        [
            {
                "description": "goodnight!",
                "comments": [
                    {"name": "dexter", "comment": "goodnight"},
                    {"name": "panda", "comment": "goodnight"},
                    {"name": "mimi", "comment": "gn"},
                    {"name": "larson", "comment": "gn!"},
                    {"name": "pepper", "comment": "Goodnight margot"},
                    {"name": "sesame", "comment": "GN"},
                    {"name": "ava", "comment": "goodnight"}
                ]
            }
        ]
    },
    {
        "name": "mimi",
        "posts": 
        [
            {
                "description": "woke up lookin like this wyd",
                "comments": [
                    {"name": "shelby", "comment": "i could easily beat you up"},
                    {"name": "bao", "comment": "gotta agree with shelby on this one"}
                ]
            }
        ]
    },
    {
        "name": "miso",
        "posts": 
        [
            {
                "description": "got any games on ur phone?",
                "comments": [
                    {"name": "shelby", "comment": "Hop on fortnite"},
                    {"name": "ollie", "comment": "Yo can I join"},
                    {"name": "larson", "comment": "im on"}
                ]
            },
            {
                "description": "on some crazy catnip right now.. woah",
                "comments": [
                    {"name": "dexter", "comment": "we gotta hang out soon"},
                    {"name": "bao", "comment": "got any left?"}
                ]
            },
            {
                "description": "had too much catnip..",
                "comments": [
                    {"name": "bao", "comment": "hmu"},
                    {"name": "ollie", "comment": "bro thats crazy"}
                ]
            }
        ]
    },
    {
        "name": "ollie",
        "posts": 
        [
            {
                "description": "thirst trap for my silly fans ;)",
                "comments": [
                    {"name": "bao", "comment": "bro no one wants to see this"},
                    {"name": "mimi", "comment": "post more pls ollie"}
                ]
            },
            {
                "description": "got my new headshots in :D",
                "comments": [
                    {"name": "paige", "comment": "this is so awesome ollie"},
                    {"name": "booboo", "comment": "lets hang out sometime!!!"},
                    {"name": "mimi", "comment": "very handsome mr ollie"}
                ]
            },
            {
                "description": "baby picture :3",
                "comments": [
                    {"name": "oreo", "comment": "back when you were cute"},
                    {"name": "ollie", "comment": "wtf man"}
                ]
            }
        ]
    },
    {
        "name": "oreo",
        "posts": 
        [
            {
                "description": "new friend yay",
                "comments": [
                    {"name": "sesame", "comment": "that's me!!!"}
                ]
            },
            {
                "description": "first time at da beach",
                "comments": [
                    {"name": "ollie", "comment": "without me?!??!?!"}
                ]
            },
            {
                "description": "haiiii :333",
                "comments": [
                    {"name": "bao", "comment": "ew"},
                    {"name": "sesame", "comment": "shut up bao your pfp is you sticking your head in a shoe"}
                ]
            }
        ]
    },
    {
        "name": "paige",
        "posts": 
        [
            {
                "description": ":3",
                "comments": [
                    {"name": "peanut", "comment": "hi ily paige"},
                    {"name": "ollie", "comment": "i pooped on that floor earlier hehehe"}
                ]
            }
        ]
    },
    {
        "name": "panda",
        "posts": 
        [
            {
                "description": "dripped out",
                "comments": [
                    {"name": "ollie", "comment": "when u dropping your workout routine?"},
                    {"name": "booboo", "comment": "need to workout sometime w/ u"},
                    {"name": "oreo", "comment": "hmu if u ever need a spotter"}
                ]
            }
        ]
    },
    {
        "name": "peanut",
        "posts": 
        [
            {
                "description": "lost in the sauce",
                "comments": [
                    {"name": "miso", "comment": "hmu cutie"}
                ]
            }
        ]
    },
    {
        "name": "pepper",
        "posts": 
        [
            {
                "description": "HAI!!!",
                "comments": [
                    {"name": "ollie", "comment": "wanna play some roblox"},
                    {"name": "ollie", "comment": "need someone to play with me"},
                    {"name": "pepper", "comment": "u suck ollie"},
                    {"name": "ollie", "comment": "SHUT UP!!!"}
                ]
            },
            {
                "description": "anyone up right now?",
                "comments": [
                    {"name": "panda", "comment": "ye get on roblox"},
                    {"name": "mimi", "comment": "can i join?"},
                    {"name": "paige", "comment": "i wanna join"},
                    {"name": "pepper", "comment": "ye ill make a group"},
                    {"name": "ollie", "comment": "got any space for me?"},
                    {"name": "ollie", "comment": "guys?"},
                    {"name": "ollie", "comment": "hello?"}
                ]
            },
            {
                "description": "sunbathing after my walk!!!",
                "comments": [
                    {"name": "oreo", "comment": "wana play some roblox?"},
                    {"name": "pepper", "comment": "k hop on"},
                    {"name": "oreo", "comment": "yippie!!!"}
                ]
            }
        ]
    },
    {
        "name": "sesame",
        "posts": 
        [
            {
                "description": "hugs!",
                "comments": [
                    {"name": "bao", "comment": "hey thats me!!!"}
                ]
            }
        ]
    },
    {
        "name": "shelby",
        "posts": 
        [
            {
                "description": "me and my gf <3",
                "comments": [
                    {"name": "bao", "comment": "dexter pls take her away from him"},
                    {"name": "bao", "comment": "he might eat her next"},
                    {"name": "dexter", "comment": "on it"}
                ]
            },
            {
                "description": "bro keeps eating my food",
                "comments": [
                    {"name": "dexter", "comment": "im literally helping you"},
                    {"name": "bao", "comment": "probably a good thing"}
                ]
            },
            {
                "description": ":3",
                "comments": [
                    {"name": "dexter", "comment": "please stop walking in the middle of the night"},
                    {"name": "dexter", "comment": "i literally wake up from the house shaking"}
                    
                ]
            },
            {
                "description": "u r wat u eat",
                "comments": [
                    {"name": "dexter", "comment": "ur fat"},
                    {"name": "sesame", "comment": "how is this even possible"},
                    {"name": "miso", "comment": "everytime you walk the earth shakes"}
                ]
            }
        ]
    },
    {
        "name": "tofu",
        "posts": 
        [
            {
                "description": "camping!!!",
                "comments": [
                    {"name": "shelby", "comment": "looks fun"},
                    {"name": "miso", "comment": "woahhhh"},
                    {"name": "oreo", "comment": "tfti"}
                ]
            }
        ]
    }
]
